pymap/__init__.py
pymap/choroplethcolourrange.py
pymap/choroplethcolourscheme.py
pymap/coordinates.py
pymap/from_csv.py
pymap/from_geojson.py
pymap/from_shapefile.py
pymap/infobox.py
pymap/mapdata.py
pymap/pymap.py
pymap/svgmap.py
geographie-0.1.2.dist-info/METADATA
geographie-0.1.2.dist-info/WHEEL
geographie-0.1.2.dist-info/top_level.txt
geographie-0.1.2.dist-info/RECORD
